Metadata-Version: 1.0
Name: azure-cli-shell
Version: 0.2.1
Summary: Microsoft Azure Command-Line Interactive Shell
Home-page: https://github.com/azure/azure-cli-shell
Author: Microsoft Corporation
Author-email: azpycli@microsoft.com
License: MIT
Platform: UNKNOWN
